parsektools/__init__.py
parsektools/isa_athmosphere.py
parsektools/isentropic_flow.py
parsektools/shock.py
parsektools/sutherland.py
parsektools-0.0.6.dist-info/METADATA
parsektools-0.0.6.dist-info/WHEEL
parsektools-0.0.6.dist-info/top_level.txt
parsektools-0.0.6.dist-info/RECORD
